[
  {
    "component": "input",
    "componentconfig": {
      "placeholder": "Your email",
      "type": "string",
      "validation": { "isRequired": true }
    },
    "field": "login",
    "label": "login",
    "type": "single",
    "value": ""
  },
  {
    "component": "inputwithicon",
    "componentconfig": {
      "hasdivider": true,
      "iconcode": "eye",
      "iconposition": "right",
      "iconsize": "sm",
      "iconstyle": "fas",
      "placeholder": "Password",
      "type": "password"
    },
    "field": "password",
    "label": "Password",
    "type": "single",
    "value": ""
  }
]
